alembic_pg_enum_generator/__init__.py
alembic_pg_enum_generator/add_enum_value_op.py
alembic_pg_enum_generator/compare_dispatch.py
alembic_pg_enum_generator/config.py
alembic_pg_enum_generator/connection.py
alembic_pg_enum_generator/declared_enums.py
alembic_pg_enum_generator/defined_enums.py
alembic_pg_enum_generator/types.py
alembic_pg_enum_generator-1.0.5.dist-info/METADATA
alembic_pg_enum_generator-1.0.5.dist-info/WHEEL
alembic_pg_enum_generator-1.0.5.dist-info/licenses/LICENSE
alembic_pg_enum_generator-1.0.5.dist-info/RECORD
