Metadata-Version: 2.4
Name: alembic-pg-enum-generator
Version: 1.0.5
Summary: Lightweight Alembic extension for PostgreSQL enum value additions using ALTER TYPE ... ADD VALUE.
Project-URL: Homepage, https://github.com/xiang9156/alembic-pg-enum-generator
Project-URL: Repository, https://github.com/xiang9156/alembic-pg-enum-generator
Project-URL: Documentation, https://github.com/xiang9156/alembic-pg-enum-generator#readme
Project-URL: Issues, https://github.com/xiang9156/alembic-pg-enum-generator/issues
Project-URL: Changelog, https://github.com/xiang9156/alembic-pg-enum-generator/blob/main/CHANGELOG.md
Author-email: Xiang Zhang <xiang9156@users.noreply.github.com>
Maintainer-email: Xiang Zhang <xiang9156@users.noreply.github.com>
License-Expression: MIT
License-File: LICENSE
Keywords: alembic,database,enum,migration,postgresql,sqlalchemy
Classifier: Development Status :: 4 - Beta
Classifier: Intended Audience :: Developers
Classifier: License :: OSI Approved :: MIT License
Classifier: Programming Language :: Python :: 3
Classifier: Programming Language :: Python :: 3.8
Classifier: Programming Language :: Python :: 3.9
Classifier: Programming Language :: Python :: 3.10
Classifier: Programming Language :: Python :: 3.11
Classifier: Programming Language :: Python :: 3.12
Classifier: Programming Language :: Python :: 3.13
Classifier: Topic :: Database
Classifier: Topic :: Database :: Database Engines/Servers
Classifier: Topic :: Software Development :: Libraries :: Python Modules
Requires-Python: >=3.8
Requires-Dist: alembic>=1.0.0
Requires-Dist: sqlalchemy>=1.4.0
Provides-Extra: dev
Requires-Dist: build; extra == 'dev'
Requires-Dist: mypy; extra == 'dev'
Requires-Dist: pre-commit; extra == 'dev'
Requires-Dist: pytest-asyncio; extra == 'dev'
Requires-Dist: pytest-cov; extra == 'dev'
Requires-Dist: pytest>=6.0; extra == 'dev'
Requires-Dist: ruff; extra == 'dev'
Requires-Dist: twine; extra == 'dev'
Provides-Extra: test
Requires-Dist: docker; extra == 'test'
Requires-Dist: psycopg2-binary; extra == 'test'
Requires-Dist: pytest-asyncio; extra == 'test'
Requires-Dist: pytest-cov; extra == 'test'
Requires-Dist: pytest>=6.0; extra == 'test'
